shardedstore.py
shardedstore-0.3.1.dist-info/LICENSE
shardedstore-0.3.1.dist-info/WHEEL
shardedstore-0.3.1.dist-info/METADATA
shardedstore-0.3.1.dist-info/RECORD
